{
  "variants": {
    "axis=x,state=0": {
      "model": "lcc:block/bomb_board_block_0_horizontal",
      "x": 90,
      "y": 90
    },
    "axis=x,state=1": {
      "model": "lcc:block/bomb_board_block_1_horizontal",
      "x": 90,
      "y": 90
    },
    "axis=x,state=10": {
      "model": "lcc:block/bomb_board_block_mine_horizontal",
      "x": 90,
      "y": 90
    },
    "axis=x,state=2": {
      "model": "lcc:block/bomb_board_block_2_horizontal",
      "x": 90,
      "y": 90
    },
    "axis=x,state=3": {
      "model": "lcc:block/bomb_board_block_3_horizontal",
      "x": 90,
      "y": 90
    },
    "axis=x,state=4": {
      "model": "lcc:block/bomb_board_block_4_horizontal",
      "x": 90,
      "y": 90
    },
    "axis=x,state=5": {
      "model": "lcc:block/bomb_board_block_5_horizontal",
      "x": 90,
      "y": 90
    },
    "axis=x,state=6": {
      "model": "lcc:block/bomb_board_block_6_horizontal",
      "x": 90,
      "y": 90
    },
    "axis=x,state=7": {
      "model": "lcc:block/bomb_board_block_7_horizontal",
      "x": 90,
      "y": 90
    },
    "axis=x,state=8": {
      "model": "lcc:block/bomb_board_block_8_horizontal",
      "x": 90,
      "y": 90
    },
    "axis=x,state=9": {
      "model": "lcc:block/bomb_board_block_horizontal",
      "x": 90,
      "y": 90
    },
    "axis=y,state=0": {
      "model": "lcc:block/bomb_board_block_0",
      "x": 0,
      "y": 0
    },
    "axis=y,state=1": {
      "model": "lcc:block/bomb_board_block_1",
      "x": 0,
      "y": 0
    },
    "axis=y,state=10": {
      "model": "lcc:block/bomb_board_block_mine",
      "x": 0,
      "y": 0
    },
    "axis=y,state=2": {
      "model": "lcc:block/bomb_board_block_2",
      "x": 0,
      "y": 0
    },
    "axis=y,state=3": {
      "model": "lcc:block/bomb_board_block_3",
      "x": 0,
      "y": 0
    },
    "axis=y,state=4": {
      "model": "lcc:block/bomb_board_block_4",
      "x": 0,
      "y": 0
    },
    "axis=y,state=5": {
      "model": "lcc:block/bomb_board_block_5",
      "x": 0,
      "y": 0
    },
    "axis=y,state=6": {
      "model": "lcc:block/bomb_board_block_6",
      "x": 0,
      "y": 0
    },
    "axis=y,state=7": {
      "model": "lcc:block/bomb_board_block_7",
      "x": 0,
      "y": 0
    },
    "axis=y,state=8": {
      "model": "lcc:block/bomb_board_block_8",
      "x": 0,
      "y": 0
    },
    "axis=y,state=9": {
      "model": "lcc:block/bomb_board_block",
      "x": 0,
      "y": 0
    },
    "axis=z,state=0": {
      "model": "lcc:block/bomb_board_block_0_horizontal",
      "x": 90,
      "y": 0
    },
    "axis=z,state=1": {
      "model": "lcc:block/bomb_board_block_1_horizontal",
      "x": 90,
      "y": 0
    },
    "axis=z,state=10": {
      "model": "lcc:block/bomb_board_block_mine_horizontal",
      "x": 90,
      "y": 0
    },
    "axis=z,state=2": {
      "model": "lcc:block/bomb_board_block_2_horizontal",
      "x": 90,
      "y": 0
    },
    "axis=z,state=3": {
      "model": "lcc:block/bomb_board_block_3_horizontal",
      "x": 90,
      "y": 0
    },
    "axis=z,state=4": {
      "model": "lcc:block/bomb_board_block_4_horizontal",
      "x": 90,
      "y": 0
    },
    "axis=z,state=5": {
      "model": "lcc:block/bomb_board_block_5_horizontal",
      "x": 90,
      "y": 0
    },
    "axis=z,state=6": {
      "model": "lcc:block/bomb_board_block_6_horizontal",
      "x": 90,
      "y": 0
    },
    "axis=z,state=7": {
      "model": "lcc:block/bomb_board_block_7_horizontal",
      "x": 90,
      "y": 0
    },
    "axis=z,state=8": {
      "model": "lcc:block/bomb_board_block_8_horizontal",
      "x": 90,
      "y": 0
    },
    "axis=z,state=9": {
      "model": "lcc:block/bomb_board_block_horizontal",
      "x": 90,
      "y": 0
    }
  }
}