{
  "parent": "minecraft:recipes/root",
  "rewards": {
    "recipes": [
      "aimagg:topaz/sword"
    ]
  },
  "criteria": {
    "has_topaz": {
      "trigger": "minecraft:inventory_changed",
      "conditions": {
        "items": [
          {
            "item": "aimagg:ingot",
            "data": 2
          }
        ]
      }
    },
    "has_the_recipe": {
      "trigger": "minecraft:recipe_unlocked",
      "conditions": {
        "recipe": "aimagg:topaz/sword"
      }
    }
  },
  "requirements": [
    [
      "has_topaz",
      "has_the_recipe"
    ]
  ]
}