{
  "parent": "minecraft:recipes/root",
  "rewards": {
    "recipes": [
      "lcc:classic_iron_block_from_storage_blocks_iron_rift"
    ]
  },
  "criteria": {
    "has_storage_blocks_iron": {
      "trigger": "minecraft:inventory_changed",
      "conditions": {
        "items": [
          {
            "tag": "forge:storage_blocks/iron"
          }
        ]
      }
    },
    "has_the_recipe": {
      "trigger": "minecraft:recipe_unlocked",
      "conditions": {
        "recipe": "lcc:classic_iron_block_from_storage_blocks_iron_rift"
      }
    }
  },
  "requirements": [
    [
      "has_storage_blocks_iron",
      "has_the_recipe"
    ]
  ]
}