{
  "parent": "minecraft:recipes/root",
  "rewards": {
    "recipes": [
      "aimagg:sapphire/axe"
    ]
  },
  "criteria": {
    "has_sapphire": {
      "trigger": "minecraft:inventory_changed",
      "conditions": {
        "items": [
          {
            "item": "aimagg:ingot",
            "data": 1
          }
        ]
      }
    },
    "has_the_recipe": {
      "trigger": "minecraft:recipe_unlocked",
      "conditions": {
        "recipe": "aimagg:sapphire/axe"
      }
    }
  },
  "requirements": [
    [
      "has_sapphire",
      "has_the_recipe"
    ]
  ]
}